cooked_input/__init__.py
cooked_input/cleaners.py
cooked_input/convertors.py
cooked_input/error_callbacks.py
cooked_input/get_input.py
cooked_input/get_table.py
cooked_input/input_utils.py
cooked_input/validators.py
cooked_input/version.py
cooked_input/examples/cleaners.py
cooked_input/examples/commands.py
cooked_input/examples/custom_ccv.py
cooked_input/examples/events.py
cooked_input/examples/get_database.py
cooked_input/examples/get_ints.py
cooked_input/examples/get_lists.py
cooked_input/examples/get_menu.py
cooked_input/examples/get_passwords.py
cooked_input/examples/get_phone_number.py
cooked_input/examples/get_strs.py
cooked_input/examples/get_table_input.py
cooked_input/examples/get_unicode.py
cooked_input/examples/get_user_info.py
cooked_input/examples/get_using_prompt_toolkit.py
cooked_input/examples/simple_input.py
cooked_input/examples/test_custom_ccv.py
cooked_input/examples/tk_get_page_list.py
cooked_input/examples/validate_tk.py
cooked_input/tests/__init__.py
cooked_input/tests/test_cleaners.py
cooked_input/tests/test_convertors.py
cooked_input/tests/test_create_table.py
cooked_input/tests/test_get_float.py
cooked_input/tests/test_get_int.py
cooked_input/tests/test_get_list.py
cooked_input/tests/test_get_str.py
cooked_input/tests/test_not_in_err_fmt.py
cooked_input/tests/test_utils.py
cooked_input/tests/test_validate.py
cooked_input/tests/utils.py
cooked_input-0.5.4.dist-info/LICENSE
cooked_input-0.5.4.dist-info/LICENSE.txt
cooked_input-0.5.4.dist-info/METADATA
cooked_input-0.5.4.dist-info/WHEEL
cooked_input-0.5.4.dist-info/top_level.txt
cooked_input-0.5.4.dist-info/RECORD
