Metadata-Version: 2.1
Name: cooked-input
Version: 0.5.4
Summary: Get, clean, convert and validate input.
Home-page: https://github.com/lwanger/cooked_input
Author: Len Wanger
Author-email: len_wanger@hotmail.com
License: MIT
Keywords: command line tool development input raw_input
Platform: UNKNOWN
Classifier: Development Status :: 5 - Production/Stable
Classifier: Intended Audience :: Developers
Classifier: License :: OSI Approved :: MIT License
Classifier: Topic :: Database :: Front-Ends
Classifier: Topic :: Software Development
Classifier: Programming Language :: Python :: 2
Classifier: Programming Language :: Python :: 2.7
Classifier: Programming Language :: Python :: 3
Classifier: Programming Language :: Python :: 3.4
Classifier: Programming Language :: Python :: 3.5
Classifier: Programming Language :: Python :: 3.6
Classifier: Programming Language :: Python :: 3.7
Classifier: Programming Language :: Python :: 3.8
Classifier: Programming Language :: Python :: 3.9
Requires-Python: >=2.7,!=3.0.*,!=3.1.*,!=3.2.*,!=3.3.*
Requires-Dist: setuptools-git
Requires-Dist: future
Requires-Dist: veryprettytable
Requires-Dist: dateparser
Requires-Dist: validus
